cal_cabb/__init__.py
cal_cabb/casa.py
cal_cabb/logger.py
cal_cabb/miriad.py
cal_cabb/cli/atca_cal.py
cal_cabb-0.1.0.dist-info/METADATA
cal_cabb-0.1.0.dist-info/WHEEL
cal_cabb-0.1.0.dist-info/entry_points.txt
cal_cabb-0.1.0.dist-info/top_level.txt
cal_cabb-0.1.0.dist-info/RECORD
